syda/__init__.py
syda/custom_generators.py
syda/dependency_handler.py
syda/generate.py
syda/llm.py
syda/output.py
syda/schema_loader.py
syda/schemas.py
syda/templates.py
syda/unstructured.py
syda/utils.py
syda-0.0.4.dist-info/licenses/LICENSE
syda-0.0.4.dist-info/METADATA
syda-0.0.4.dist-info/WHEEL
syda-0.0.4.dist-info/top_level.txt
syda-0.0.4.dist-info/RECORD
