Metadata-Version: 2.4
Name: syda
Version: 0.0.4
Summary: Seamlessly generates realistic synthetic test data—including structured, unstructured, PDF, and HTML—using AI and large language models. It preserves referential integrity, maintains privacy compliance, and accelerates development workflows. SYDA enables both highly regulated industries such as healthcare and banking, as well as non-regulated environments like software testing, research, and analytics, to safely simulate diverse data scenarios without exposing sensitive information.
Author-email: Rama Krishna Kumar Lingamgunta <ramkumar2606@gmail.com>
License: MIT
Project-URL: Homepage, https://github.com/syda-ai/syda
Project-URL: Documentation, https://python.syda.ai
Project-URL: Repository, https://github.com/syda-ai/syda.git
Project-URL: Issues, https://github.com/syda-ai/syda/issues
Project-URL: Changelog, https://github.com/syda-ai/syda/blob/main/CHANGELOG.md
Keywords: synthetic data,AI,machine learning,data generation,testing,privacy,SQLAlchemy,OpenAI,AzureOpenAI,Anthropic,Claude,Google,Gemini,xAI,Grok,GPT
Classifier: Development Status :: 5 - Production/Stable
Classifier: Intended Audience :: Developers
Classifier: Intended Audience :: Science/Research
Classifier: License :: OSI Approved :: MIT License
Classifier: Programming Language :: Python :: 3
Classifier: Programming Language :: Python :: 3.8
Classifier: Programming Language :: Python :: 3.9
Classifier: Programming Language :: Python :: 3.10
Classifier: Programming Language :: Python :: 3.11
Classifier: Programming Language :: Python :: 3.12
Classifier: Topic :: Scientific/Engineering :: Artificial Intelligence
Classifier: Topic :: Software Development :: Libraries :: Python Modules
Classifier: Topic :: Database
Classifier: Topic :: Utilities
Classifier: Operating System :: OS Independent
Classifier: Environment :: Console
Classifier: Framework :: Pydantic
Requires-Python: >=3.8
License-File: LICENSE
Requires-Dist: pydantic>=2.4.2
Requires-Dist: python-dotenv>=1.0.0
Requires-Dist: sqlalchemy>=2.0.23
Requires-Dist: pandas>=2.0.3
Requires-Dist: numpy>=1.24.3
Requires-Dist: openai>=1.0.0
Requires-Dist: anthropic>=0.7.0
Requires-Dist: python-magic>=0.4.27
Requires-Dist: python-docx>=1.0.0
Requires-Dist: openpyxl>=3.1.2
Requires-Dist: pyyaml>=6.0.1
Requires-Dist: boto3>=1.28.0
Requires-Dist: azure-storage-blob>=12.19.0
Requires-Dist: google-genai>=1.30.0
Requires-Dist: jsonref>=1.1.0
Requires-Dist: pdfplumber>=0.10.3
Requires-Dist: pillow>=10.0.1
Requires-Dist: pytesseract>=0.3.10
Requires-Dist: sqlalchemy-utils>=0.41.1
Requires-Dist: networkx>=3.1
Requires-Dist: instructor>=1.0.0
Requires-Dist: weasyprint>=65.1
Requires-Dist: jsonref>=1.1.0
Requires-Dist: google-genai>=1.30.0
Provides-Extra: dev
Requires-Dist: pytest>=7.4.0; extra == "dev"
Requires-Dist: pytest-cov>=4.0.0; extra == "dev"
Requires-Dist: pytest-asyncio>=0.21.0; extra == "dev"
Requires-Dist: black>=23.0.0; extra == "dev"
Requires-Dist: isort>=5.12.0; extra == "dev"
Requires-Dist: flake8>=6.0.0; extra == "dev"
Requires-Dist: mypy>=1.0.0; extra == "dev"
Requires-Dist: pre-commit>=3.0.0; extra == "dev"
Provides-Extra: docs
Requires-Dist: mkdocs-material>=9.6.19; extra == "docs"
Requires-Dist: mkdocs>=1.6.1; extra == "docs"
Requires-Dist: mkdocs-macros-plugin>=1.3.7; extra == "docs"
Requires-Dist: mkdocs-mermaid2-plugin>=1.1.1; extra == "docs"
Requires-Dist: mkdocs-minify-plugin>=0.8.0; extra == "docs"
Provides-Extra: test
Requires-Dist: pytest>=7.4.0; extra == "test"
Requires-Dist: pytest-cov>=4.0.0; extra == "test"
Requires-Dist: pytest-asyncio>=0.21.0; extra == "test"
Requires-Dist: pytest-mock>=3.10.0; extra == "test"
Provides-Extra: all
Requires-Dist: pytest>=7.4.0; extra == "all"
Requires-Dist: pytest-cov>=4.0.0; extra == "all"
Requires-Dist: pytest-asyncio>=0.21.0; extra == "all"
Requires-Dist: pytest-mock>=3.10.0; extra == "all"
Requires-Dist: black>=23.0.0; extra == "all"
Requires-Dist: isort>=5.12.0; extra == "all"
Requires-Dist: flake8>=6.0.0; extra == "all"
Requires-Dist: mypy>=1.0.0; extra == "all"
Requires-Dist: pre-commit>=3.0.0; extra == "all"
Requires-Dist: mkdocs-material>=9.6.15; extra == "all"
Requires-Dist: mkdocs>=1.6.1; extra == "all"
Requires-Dist: mkdocs-macros-plugin>=1.3.7; extra == "all"
Requires-Dist: mkdocs-mermaid2-plugin>=1.1.1; extra == "all"
Dynamic: license-file
